payping/__init__.py
payping/authentication.py
payping/payment.py
payping-0.0.4.dist-info/LICENSE
payping-0.0.4.dist-info/METADATA
payping-0.0.4.dist-info/WHEEL
payping-0.0.4.dist-info/top_level.txt
payping-0.0.4.dist-info/RECORD
