Metadata-Version: 2.1
Name: payping
Version: 0.0.4
Summary: manage payping.ir web service
Home-page: https://github.com/rahimaee/payping.git
Author: mohammad reza rahimaee
Author-email: mohammad.rahimaee@gmail.com
License: UNKNOWN
Project-URL: Bug Tracker, https://github.com/rahimaee/payping/issues
Platform: UNKNOWN
Classifier: Programming Language :: Python :: 3
Classifier: License :: OSI Approved :: MIT License
Classifier: Operating System :: OS Independent
Requires-Python: >=3.7
License-File: LICENSE
Requires-Dist: requests
Requires-Dist: certifi
Requires-Dist: charset-normalizer
Requires-Dist: idna
Requires-Dist: urllib3
